{
    "kind": "youtube#searchListResponse",
    "etag": "ce1wpaWTkbxlrEn6HBoIILEvz30",
    "nextPageToken": "CDIQAA",
    "regionCode": "BD",
    "pageInfo": {
        "totalResults": 195919,
        "resultsPerPage": 50
    },
    "items": [
        {
            "kind": "youtube#searchResult",
            "etag": "fK5g_kY9ZMjPPlVoHgBd76Wf4FY",
            "id": {
                "kind": "youtube#channel",
                "channelId": "UCIovvGEUd3v7RPOz3EAs8HA"
            },
            "snippet": {
                "publishedAt": "2020-07-19T16:50:46Z",
                "channelId": "UCIovvGEUd3v7RPOz3EAs8HA",
                "title": "Hello Noyon",
                "description": "\u09ab\u09b0\u09ae\u09be\u09b2\u09bf\u09a8\u09ae\u09c1\u0995\u09cd\u09a4 \u09ac\u09bf\u09a8\u09cb\u09a6\u09a8 \u0995\u09c7\u09a8\u09cd\u09a6\u09cd\u09b0.",
                "thumbnails": {
                    "default": {
                        "url": "https://yt3.ggpht.com/Hda8k-SuhjGoHeFsylcbGS8IvHaTCtve71Zm5xi_kM36bCzwPQFf_SqTl_6togTEfbaSJ1G8Fg=s88-c-k-c0xffffffff-no-rj-mo"
                    },
                    "medium": {
                        "url": "https://yt3.ggpht.com/Hda8k-SuhjGoHeFsylcbGS8IvHaTCtve71Zm5xi_kM36bCzwPQFf_SqTl_6togTEfbaSJ1G8Fg=s240-c-k-c0xffffffff-no-rj-mo"
                    },
                    "high": {
                        "url": "https://yt3.ggpht.com/Hda8k-SuhjGoHeFsylcbGS8IvHaTCtve71Zm5xi_kM36bCzwPQFf_SqTl_6togTEfbaSJ1G8Fg=s800-c-k-c0xffffffff-no-rj-mo"
                    }
                },
                "channelTitle": "Hello Noyon",
                "liveBroadcastContent": "none",
                "publishTime": "2020-07-19T16:50:46Z"
            }
        },
        {
            "kind": "youtube#searchResult",
            "etag": "g3_QJIRNaqpcfkFDzZ8smZAFRyo",
            "id": {
                "kind": "youtube#channel",
                "channelId": "UCBW4OrkWHsXQKyGervMRiRQ"
            },
            "snippet": {
                "publishedAt": "2022-08-03T07:26:38Z",
                "channelId": "UCBW4OrkWHsXQKyGervMRiRQ",
                "title": "Hello Cartoon",
                "description": "\u0986\u09aa\u09a8\u09be\u09a6\u09c7\u09b0 \u09b8\u09ac\u09be\u0987\u0995\u09c7 \u0986\u09ae\u09be\u09a6\u09c7\u09b0 \u098f\u0987 \u099a\u09cd\u09af\u09be\u09a8\u09c7\u09b2 \u09b8\u09cd\u09ac\u09be\u0997\u09a4\u09ae\u0964 \u0986\u09ae\u09be\u09a6\u09c7\u09b0 \u098f\u0987 \u099a\u09cd\u09af\u09be\u09a8\u09c7\u09b2\u09c7 ...",
                "thumbnails": {
                    "default": {
                        "url": "https://yt3.ggpht.com/5ERgl3_TuRZvy_omEOOhNPf9jP2BUIQanI1Xl4htyIaaV96kbo7BA3avGJattieE4Mezx9-Aihs=s88-c-k-c0xffffffff-no-rj-mo"
                    },
                    "medium": {
                        "url": "https://yt3.ggpht.com/5ERgl3_TuRZvy_omEOOhNPf9jP2BUIQanI1Xl4htyIaaV96kbo7BA3avGJattieE4Mezx9-Aihs=s240-c-k-c0xffffffff-no-rj-mo"
                    },
                    "high": {
                        "url": "https://yt3.ggpht.com/5ERgl3_TuRZvy_omEOOhNPf9jP2BUIQanI1Xl4htyIaaV96kbo7BA3avGJattieE4Mezx9-Aihs=s800-c-k-c0xffffffff-no-rj-mo"
                    }
                },
                "channelTitle": "Hello Cartoon",
                "liveBroadcastContent": "none",
                "publishTime": "2022-08-03T07:26:38Z"
            }
        },
        {
            "kind": "youtube#searchResult",
            "etag": "w2GXg1L0IUBpv0GDB5dIdr00txw",
            "id": {
                "kind": "youtube#channel",
                "channelId": "UC5YGzpexD_3E9LZQIj5EVPQ"
            },
            "snippet": {
                "publishedAt": "2017-10-15T13:12:43Z",
                "channelId": "UC5YGzpexD_3E9LZQIj5EVPQ",
                "title": "Hello Bd Money Maker",
                "description": "Hello BD Money Maker! \u0986\u09ae\u09bf \u099c\u09a8\u09bf \u0986\u09b2\u09ae, \u0986\u09b6\u09be \u0995\u09b0\u09bf \u0986\u09aa\u09a8\u09be\u09b0\u09be \u09b8\u09ac\u09be\u0987 \u09ad\u09be\u09b2 \u0986\u099b\u09c7\u09a8 ? \u09aa\u09cd\u09b0\u09a4\u09bf\u09a6\u09bf\u09a8 \u098f\u0995\u099f\u09bf ...",
                "thumbnails": {
                    "default": {
                        "url": "https://yt3.ggpht.com/ytc/AL5GRJVDIfJmZhHxK0YI6BlZQM-kldQ1RIO9TmvnFrJP=s88-c-k-c0xffffffff-no-rj-mo"
                    },
                    "medium": {
                        "url": "https://yt3.ggpht.com/ytc/AL5GRJVDIfJmZhHxK0YI6BlZQM-kldQ1RIO9TmvnFrJP=s240-c-k-c0xffffffff-no-rj-mo"
                    },
                    "high": {
                        "url": "https://yt3.ggpht.com/ytc/AL5GRJVDIfJmZhHxK0YI6BlZQM-kldQ1RIO9TmvnFrJP=s800-c-k-c0xffffffff-no-rj-mo"
                    }
                },
                "channelTitle": "Hello Bd Money Maker",
                "liveBroadcastContent": "upcoming",
                "publishTime": "2017-10-15T13:12:43Z"
            }
        },
        {
            "kind": "youtube#searchResult",
            "etag": "lX7mOgA54K0s_L7Kh7kn6GzEthM",
            "id": {
                "kind": "youtube#channel",
                "channelId": "UCz1JwruCJxOPfuQdSN-hQiw"
            },
            "snippet": {
                "publishedAt": "2021-01-12T00:21:53Z",
                "channelId": "UCz1JwruCJxOPfuQdSN-hQiw",
                "title": "Hello 24",
                "description": "''HELLO 24 CHANNEL'' This is an entertainment channel . The videos and shorts are created by me. Stay with my channel. thank ...",
                "thumbnails": {
                    "default": {
                        "url": "https://yt3.ggpht.com/ytc/AL5GRJVL8SRF7fPAHmjPqzm-JRK2rlfu7_M6_wSE4QaT=s88-c-k-c0xffffffff-no-rj-mo"
                    },
                    "medium": {
                        "url": "https://yt3.ggpht.com/ytc/AL5GRJVL8SRF7fPAHmjPqzm-JRK2rlfu7_M6_wSE4QaT=s240-c-k-c0xffffffff-no-rj-mo"
                    },
                    "high": {
                        "url": "https://yt3.ggpht.com/ytc/AL5GRJVL8SRF7fPAHmjPqzm-JRK2rlfu7_M6_wSE4QaT=s800-c-k-c0xffffffff-no-rj-mo"
                    }
                },
                "channelTitle": "Hello 24",
                "liveBroadcastContent": "none",
                "publishTime": "2021-01-12T00:21:53Z"
            }
        },
        {
            "kind": "youtube#searchResult",
            "etag": "pL5Sv3iZMK5Gtn8EFdrSRIOGyf8",
            "id": {
                "kind": "youtube#channel",
                "channelId": "UCxUo-e6OQ1sjuP78j9cSJFg"
            },
            "snippet": {
                "publishedAt": "2021-06-11T14:13:46Z",
                "channelId": "UCxUo-e6OQ1sjuP78j9cSJFg",
                "title": "Hello Banglar Manush",
                "description": "Welcome to the official YouTube Channel of Hello Banglar Manush ( \u09b9\u09cd\u09af\u09be\u09b2\u09cb \u09ac\u09be\u0982\u09b2\u09be\u09b0 \u09ae\u09be\u09a8\u09c1\u09b7 ) HBM. Our aim is to ...",
                "thumbnails": {
                    "default": {
                        "url": "https://yt3.ggpht.com/fY0O7qg4xdQ1keGvDbJYSQOVxLDnHFMgP6PNKUPCs3Gkjsl_roYP0ujDyJJaX64RPqQbq7Lbyw=s88-c-k-c0xffffffff-no-rj-mo"
                    },
                    "medium": {
                        "url": "https://yt3.ggpht.com/fY0O7qg4xdQ1keGvDbJYSQOVxLDnHFMgP6PNKUPCs3Gkjsl_roYP0ujDyJJaX64RPqQbq7Lbyw=s240-c-k-c0xffffffff-no-rj-mo"
                    },
                    "high": {
                        "url": "https://yt3.ggpht.com/fY0O7qg4xdQ1keGvDbJYSQOVxLDnHFMgP6PNKUPCs3Gkjsl_roYP0ujDyJJaX64RPqQbq7Lbyw=s800-c-k-c0xffffffff-no-rj-mo"
                    }
                },
                "channelTitle": "Hello Banglar Manush",
                "liveBroadcastContent": "none",
                "publishTime": "2021-06-11T14:13:46Z"
            }
        },
        {
            "kind": "youtube#searchResult",
            "etag": "Q63GmhUSYNlizy6XXKroBzeag00",
            "id": {
                "kind": "youtube#channel",
                "channelId": "UCshx7jvc8q3F0qx4jnPNm-Q"
            },
            "snippet": {
                "publishedAt": "2022-12-19T17:28:48Z",
                "channelId": "UCshx7jvc8q3F0qx4jnPNm-Q",
                "title": "Hello",
                "description": "Hello\" Guys I am New You Tuber To please Support My Hello You Tube Channel Thanks.",
                "thumbnails": {
                    "default": {
                        "url": "https://yt3.ggpht.com/jB4coPG3gZ_s0Kic17RLZLWirhNLcTSxZ5IGaMl15GiDxzKRi7PMnrSTxsjU1kk-5TrU3afNSQ=s88-c-k-c0xffffffff-no-rj-mo"
                    },
                    "medium": {
                        "url": "https://yt3.ggpht.com/jB4coPG3gZ_s0Kic17RLZLWirhNLcTSxZ5IGaMl15GiDxzKRi7PMnrSTxsjU1kk-5TrU3afNSQ=s240-c-k-c0xffffffff-no-rj-mo"
                    },
                    "high": {
                        "url": "https://yt3.ggpht.com/jB4coPG3gZ_s0Kic17RLZLWirhNLcTSxZ5IGaMl15GiDxzKRi7PMnrSTxsjU1kk-5TrU3afNSQ=s800-c-k-c0xffffffff-no-rj-mo"
                    }
                },
                "channelTitle": "Hello",
                "liveBroadcastContent": "none",
                "publishTime": "2022-12-19T17:28:48Z"
            }
        },
        {
            "kind": "youtube#searchResult",
            "etag": "_0ClycdvsQNkJIxs7tIGFMIUXmw",
            "id": {
                "kind": "youtube#channel",
                "channelId": "UC4PenTl_MO3-Mh77J7lZk5w"
            },
            "snippet": {
                "publishedAt": "2022-03-31T10:57:40Z",
                "channelId": "UC4PenTl_MO3-Mh77J7lZk5w",
                "title": "HELLO HOUSE",
                "description": "Hello~, this is Hello House.",
                "thumbnails": {
                    "default": {
                        "url": "https://yt3.ggpht.com/_Lilr-BKZtRIGPmEWf-78l43Xf65lLJ_r1i7Pva7gPngyHImJkxyTKkucL90IepX0OJGz1r1Vw=s88-c-k-c0xffffffff-no-rj-mo"
                    },
                    "medium": {
                        "url": "https://yt3.ggpht.com/_Lilr-BKZtRIGPmEWf-78l43Xf65lLJ_r1i7Pva7gPngyHImJkxyTKkucL90IepX0OJGz1r1Vw=s240-c-k-c0xffffffff-no-rj-mo"
                    },
                    "high": {
                        "url": "https://yt3.ggpht.com/_Lilr-BKZtRIGPmEWf-78l43Xf65lLJ_r1i7Pva7gPngyHImJkxyTKkucL90IepX0OJGz1r1Vw=s800-c-k-c0xffffffff-no-rj-mo"
                    }
                },
                "channelTitle": "HELLO HOUSE",
                "liveBroadcastContent": "none",
                "publishTime": "2022-03-31T10:57:40Z"
            }
        },
        {
            "kind": "youtube#searchResult",
            "etag": "fuYRpEu-xwxtNLGh52hJ3GcG3E4",
            "id": {
                "kind": "youtube#channel",
                "channelId": "UCA_1GyHRLv-F9PEtZZ5qn9w"
            },
            "snippet": {
                "publishedAt": "2019-06-09T13:07:45Z",
                "channelId": "UCA_1GyHRLv-F9PEtZZ5qn9w",
                "title": "Hello Duniya / \u09b9\u09cd\u09af\u09be\u09b2\u09cb \u09a6\u09c1\u09a8\u09bf\u09af\u09bc\u09be",
                "description": "\u09ac\u09bf\u09b6\u09cd\u09ac\u09be\u09af\u09bc\u09a8 \u0993 \u09a4\u09a5\u09cd\u09af \u09aa\u09cd\u09b0\u09af\u09c1\u0995\u09cd\u09a4\u09bf\u09b0 \u09af\u09c1\u0997\u09c7 \u09ac\u09b8\u09ac\u09be\u09b8 \u0995\u09b0\u09c7 \u0995\u09c7\u09a8 \u0986\u09ae\u09be\u09a6\u09c7\u09b0 \u09ae\u09be\u09a8\u09b8\u09aa\u099f\u09c7 \u0986\u099c\u0993 ...",
                "thumbnails": {
                    "default": {
                        "url": "https://yt3.ggpht.com/ytc/AL5GRJWZZTgZwaY9qtTClW_cjzta24fUQuEAC8RbuuYS=s88-c-k-c0xffffffff-no-rj-mo"
                    },
                    "medium": {
                        "url": "https://yt3.ggpht.com/ytc/AL5GRJWZZTgZwaY9qtTClW_cjzta24fUQuEAC8RbuuYS=s240-c-k-c0xffffffff-no-rj-mo"
                    },
                    "high": {
                        "url": "https://yt3.ggpht.com/ytc/AL5GRJWZZTgZwaY9qtTClW_cjzta24fUQuEAC8RbuuYS=s800-c-k-c0xffffffff-no-rj-mo"
                    }
                },
                "channelTitle": "Hello Duniya / \u09b9\u09cd\u09af\u09be\u09b2\u09cb \u09a6\u09c1\u09a8\u09bf\u09af\u09bc\u09be",
                "liveBroadcastContent": "none",
                "publishTime": "2019-06-09T13:07:45Z"
            }
        },
        {
            "kind": "youtube#searchResult",
            "etag": "wZA_x2ZcYfbwzv8QlN6u3vY_dUY",
            "id": {
                "kind": "youtube#channel",
                "channelId": "UCkYcFrVCxWRp6hxkKrlueQA"
            },
            "snippet": {
                "publishedAt": "2016-09-17T13:13:01Z",
                "channelId": "UCkYcFrVCxWRp6hxkKrlueQA",
                "title": "bdnews24.com Hello",
                "description": "",
                "thumbnails": {
                    "default": {
                        "url": "https://yt3.ggpht.com/ytc/AL5GRJUili25WF2AbGE0KzkJnr7W7Ckv898XOfndtTX6=s88-c-k-c0xffffffff-no-rj-mo"
                    },
                    "medium": {
                        "url": "https://yt3.ggpht.com/ytc/AL5GRJUili25WF2AbGE0KzkJnr7W7Ckv898XOfndtTX6=s240-c-k-c0xffffffff-no-rj-mo"
                    },
                    "high": {
                        "url": "https://yt3.ggpht.com/ytc/AL5GRJUili25WF2AbGE0KzkJnr7W7Ckv898XOfndtTX6=s800-c-k-c0xffffffff-no-rj-mo"
                    }
                },
                "channelTitle": "bdnews24.com Hello",
                "liveBroadcastContent": "none",
                "publishTime": "2016-09-17T13:13:01Z"
            }
        },
        {
            "kind": "youtube#searchResult",
            "etag": "DsV_pFoqcYrqsW_IoLjxcjcp0gw",
            "id": {
                "kind": "youtube#channel",
                "channelId": "UCF526cda7rMmK7Zd5VybSNg"
            },
            "snippet": {
                "publishedAt": "2019-12-03T17:08:22Z",
                "channelId": "UCF526cda7rMmK7Zd5VybSNg",
                "title": "\ud835\udc6f\ud835\udc86\ud835\udc8d\ud835\udc8d\ud835\udc90 \ud835\udc7a\ud835\udc89\ud835\udc86\ud835\udc93\ud835\udc91\ud835\udc96\ud835\udc93",
                "description": "Hello Sherpur \u0987\u0989\u099f\u09bf\u0989\u09ac \u099a\u09cd\u09af\u09be\u09a8\u09c7\u09b2\u09c7 \u0986\u09aa\u09a8\u09be\u0995\u09c7 \u09b8\u09cd\u09ac\u09be\u0997\u09a4\u09ae\u0964 \u09b6\u09c7\u09b0\u09aa\u09c1\u09b0 \u099c\u09c7\u09b2\u09be \u09b8\u09ae\u09cd\u09aa\u09b0\u09cd\u0995\u09c7 ...",
                "thumbnails": {
                    "default": {
                        "url": "https://yt3.ggpht.com/XEcm1src5nQDZH0QhY17TXBqyPQrTUhkkXmuFmiGvsfCiILZXnE52fEpMxHnOMRsXZBXr9MG=s88-c-k-c0xffffffff-no-rj-mo"
                    },
                    "medium": {
                        "url": "https://yt3.ggpht.com/XEcm1src5nQDZH0QhY17TXBqyPQrTUhkkXmuFmiGvsfCiILZXnE52fEpMxHnOMRsXZBXr9MG=s240-c-k-c0xffffffff-no-rj-mo"
                    },
                    "high": {
                        "url": "https://yt3.ggpht.com/XEcm1src5nQDZH0QhY17TXBqyPQrTUhkkXmuFmiGvsfCiILZXnE52fEpMxHnOMRsXZBXr9MG=s800-c-k-c0xffffffff-no-rj-mo"
                    }
                },
                "channelTitle": "\ud835\udc6f\ud835\udc86\ud835\udc8d\ud835\udc8d\ud835\udc90 \ud835\udc7a\ud835\udc89\ud835\udc86\ud835\udc93\ud835\udc91\ud835\udc96\ud835\udc93",
                "liveBroadcastContent": "none",
                "publishTime": "2019-12-03T17:08:22Z"
            }
        },
        {
            "kind": "youtube#searchResult",
            "etag": "xoUb7w4z5P6rTQMGqCqMHVCOAzw",
            "id": {
                "kind": "youtube#channel",
                "channelId": "UCarYIx_TePhiXRBvKA-NZvw"
            },
            "snippet": {
                "publishedAt": "2020-08-31T14:21:51Z",
                "channelId": "UCarYIx_TePhiXRBvKA-NZvw",
                "title": "Hello Rannaghor",
                "description": "Welcome to my Hello Rannaghor. Easy way to learn cooking any Bangladeshi iteams, Bangla Recipe, Bangla Ranna, New ...",
                "thumbnails": {
                    "default": {
                        "url": "https://yt3.ggpht.com/ytc/AL5GRJWh1jww5MZxLOmCS711ixUYmGuM18v07m6Vzqc0Rg=s88-c-k-c0xffffffff-no-rj-mo"
                    },
                    "medium": {
                        "url": "https://yt3.ggpht.com/ytc/AL5GRJWh1jww5MZxLOmCS711ixUYmGuM18v07m6Vzqc0Rg=s240-c-k-c0xffffffff-no-rj-mo"
                    },
                    "high": {
                        "url": "https://yt3.ggpht.com/ytc/AL5GRJWh1jww5MZxLOmCS711ixUYmGuM18v07m6Vzqc0Rg=s800-c-k-c0xffffffff-no-rj-mo"
                    }
                },
                "channelTitle": "Hello Rannaghor",
                "liveBroadcastContent": "none",
                "publishTime": "2020-08-31T14:21:51Z"
            }
        },
        {
            "kind": "youtube#searchResult",
            "etag": "RntPqktTmM8Za0T0AFI6hC2MTMU",
            "id": {
                "kind": "youtube#channel",
                "channelId": "UCiCUf29nSndUQkmHRGd7Raw"
            },
            "snippet": {
                "publishedAt": "2021-03-01T13:01:36Z",
                "channelId": "UCiCUf29nSndUQkmHRGd7Raw",
                "title": "hello Asia BD",
                "description": "Hello Asia BD Singapore visa information about Visa interview Singapore this channel inside i show Singapore travel ' visa vlog ...",
                "thumbnails": {
                    "default": {
                        "url": "https://yt3.ggpht.com/x4wC-bRVhLxZXlZ76zcijsim28lzj-tG_OymBBzU604-wpOcyZs7V08T4aFedimLmZZZ_YzcUQ=s88-c-k-c0xffffffff-no-rj-mo"
                    },
                    "medium": {
                        "url": "https://yt3.ggpht.com/x4wC-bRVhLxZXlZ76zcijsim28lzj-tG_OymBBzU604-wpOcyZs7V08T4aFedimLmZZZ_YzcUQ=s240-c-k-c0xffffffff-no-rj-mo"
                    },
                    "high": {
                        "url": "https://yt3.ggpht.com/x4wC-bRVhLxZXlZ76zcijsim28lzj-tG_OymBBzU604-wpOcyZs7V08T4aFedimLmZZZ_YzcUQ=s800-c-k-c0xffffffff-no-rj-mo"
                    }
                },
                "channelTitle": "hello Asia BD",
                "liveBroadcastContent": "none",
                "publishTime": "2021-03-01T13:01:36Z"
            }
        },
        {
            "kind": "youtube#searchResult",
            "etag": "iJwuvVlthqXo3FeM5poZLiDobBk",
            "id": {
                "kind": "youtube#channel",
                "channelId": "UCt4oHodLr8wKKurjrScICaA"
            },
            "snippet": {
                "publishedAt": "2019-01-19T16:39:04Z",
                "channelId": "UCt4oHodLr8wKKurjrScICaA",
                "title": "Hello Barishal",
                "description": "Hi there! i am Rezaul Karim. I am going to travel all around Bangladesh and review the best food.I will try to bring the justice to you ...",
                "thumbnails": {
                    "default": {
                        "url": "https://yt3.ggpht.com/pkeybtBy5ZNF9YDedquHBcmp6hpdDtSGgCliBy0_-phuisC44rtFheq_XUIyMe1Tv6htB-c4nw=s88-c-k-c0xffffffff-no-rj-mo"
                    },
                    "medium": {
                        "url": "https://yt3.ggpht.com/pkeybtBy5ZNF9YDedquHBcmp6hpdDtSGgCliBy0_-phuisC44rtFheq_XUIyMe1Tv6htB-c4nw=s240-c-k-c0xffffffff-no-rj-mo"
                    },
                    "high": {
                        "url": "https://yt3.ggpht.com/pkeybtBy5ZNF9YDedquHBcmp6hpdDtSGgCliBy0_-phuisC44rtFheq_XUIyMe1Tv6htB-c4nw=s800-c-k-c0xffffffff-no-rj-mo"
                    }
                },
                "channelTitle": "Hello Barishal",
                "liveBroadcastContent": "upcoming",
                "publishTime": "2019-01-19T16:39:04Z"
            }
        },
        {
            "kind": "youtube#searchResult",
            "etag": "KfXepKsQY52KXHrr-1jse2wIK8I",
            "id": {
                "kind": "youtube#channel",
                "channelId": "UCdPRxVSfvuVWfIS428qiMWQ"
            },
            "snippet": {
                "publishedAt": "2021-03-27T21:41:03Z",
                "channelId": "UCdPRxVSfvuVWfIS428qiMWQ",
                "title": "HELLO Portugal",
                "description": "\u0986\u09b8\u09b8\u09be\u09b2\u09be\u09ae\u09c1 \u0986\u09b2\u09be\u0987\u0995\u09c1\u09ae\u0964 HELLO Portugal \u099a\u09cd\u09af\u09be\u09a8\u09c7\u09b2\u09c7 \u0986\u09aa\u09a8\u09be\u0995\u09c7 \u09b8\u09cd\u09ac\u09be\u0997\u09a4\u09ae\u0964 \u098f\u0987 \u099a\u09cd\u09af\u09be\u09a8\u09c7\u09b2\u099f\u09bf ...",
                "thumbnails": {
                    "default": {
                        "url": "https://yt3.ggpht.com/ytc/AL5GRJXkFzp7Rd3UglMZdtBoAtC4HYT_CIvc54jb7Ki2=s88-c-k-c0xffffffff-no-rj-mo"
                    },
                    "medium": {
                        "url": "https://yt3.ggpht.com/ytc/AL5GRJXkFzp7Rd3UglMZdtBoAtC4HYT_CIvc54jb7Ki2=s240-c-k-c0xffffffff-no-rj-mo"
                    },
                    "high": {
                        "url": "https://yt3.ggpht.com/ytc/AL5GRJXkFzp7Rd3UglMZdtBoAtC4HYT_CIvc54jb7Ki2=s800-c-k-c0xffffffff-no-rj-mo"
                    }
                },
                "channelTitle": "HELLO Portugal",
                "liveBroadcastContent": "none",
                "publishTime": "2021-03-27T21:41:03Z"
            }
        },
        {
            "kind": "youtube#searchResult",
            "etag": "hRubDQvVexWS6O3rgosoY4I_9kE",
            "id": {
                "kind": "youtube#channel",
                "channelId": "UCbjPveQ-V6Eixu7vsEjZteA"
            },
            "snippet": {
                "publishedAt": "2020-09-29T08:35:39Z",
                "channelId": "UCbjPveQ-V6Eixu7vsEjZteA",
                "title": "Hello Youtube Bangla",
                "description": "Hello guy's Hello Youtube Bangla \u099a\u09cd\u09af\u09be\u09a8\u09c7\u09b2\u09c7\u09b0 \u098f\u09b0 \u0995\u09be\u099c\u0987 \u09b9\u099a\u09cd\u099b\u09c7 \u09b6\u09bf\u0996\u09be\u09a8\u09cb\u0964 Thank you for visiting my ...",
                "thumbnails": {
                    "default": {
                        "url": "https://yt3.ggpht.com/ytc/AL5GRJVXUdAqfg_RRtqo4C4n8XmsOhrglfdjZmsrZy8G=s88-c-k-c0xffffffff-no-rj-mo"
                    },
                    "medium": {
                        "url": "https://yt3.ggpht.com/ytc/AL5GRJVXUdAqfg_RRtqo4C4n8XmsOhrglfdjZmsrZy8G=s240-c-k-c0xffffffff-no-rj-mo"
                    },
                    "high": {
                        "url": "https://yt3.ggpht.com/ytc/AL5GRJVXUdAqfg_RRtqo4C4n8XmsOhrglfdjZmsrZy8G=s800-c-k-c0xffffffff-no-rj-mo"
                    }
                },
                "channelTitle": "Hello Youtube Bangla",
                "liveBroadcastContent": "none",
                "publishTime": "2020-09-29T08:35:39Z"
            }
        },
        {
            "kind": "youtube#searchResult",
            "etag": "94Dl3UhW3qrqAEO0hzuuGT70I2k",
            "id": {
                "kind": "youtube#channel",
                "channelId": "UCvJmXsZ6Jp1tVHBwdt3T1BA"
            },
            "snippet": {
                "publishedAt": "2021-07-08T02:46:23Z",
                "channelId": "UCvJmXsZ6Jp1tVHBwdt3T1BA",
                "title": "Hello Bangladeshi Freelancers",
                "description": "Hello Freelancers \u098f\u0987 \u099a\u09cd\u09af\u09be\u09a8\u09c7\u09b2\u09c7 \u099f\u09c7\u0995\u09a8\u09cb\u09b2\u099c\u09bf \u09b0\u09bf\u09b2\u09c7\u099f\u09c7\u09a1 \u09ac\u09be \u09aa\u09cd\u09b0\u09af\u09c1\u0995\u09cd\u09a4\u09bf \u09b0\u09bf\u09b2\u09c7\u099f\u09c7\u09a1 \u09ad\u09bf\u09a1\u09bf\u0993 ...",
                "thumbnails": {
                    "default": {
                        "url": "https://yt3.ggpht.com/ThwpBlqhko5e-B4q-eDgbQRg6Kr9YugK1exIjEqLYBlf79K3W0ZSEUPsQG7ypc13zdGmom2TRe8=s88-c-k-c0xffffffff-no-rj-mo"
                    },
                    "medium": {
                        "url": "https://yt3.ggpht.com/ThwpBlqhko5e-B4q-eDgbQRg6Kr9YugK1exIjEqLYBlf79K3W0ZSEUPsQG7ypc13zdGmom2TRe8=s240-c-k-c0xffffffff-no-rj-mo"
                    },
                    "high": {
                        "url": "https://yt3.ggpht.com/ThwpBlqhko5e-B4q-eDgbQRg6Kr9YugK1exIjEqLYBlf79K3W0ZSEUPsQG7ypc13zdGmom2TRe8=s800-c-k-c0xffffffff-no-rj-mo"
                    }
                },
                "channelTitle": "Hello Bangladeshi Freelancers",
                "liveBroadcastContent": "none",
                "publishTime": "2021-07-08T02:46:23Z"
            }
        },
        {
            "kind": "youtube#searchResult",
            "etag": "4WuEX0xwsexmEWSCh2MP-CJc4yU",
            "id": {
                "kind": "youtube#channel",
                "channelId": "UCFqHLi38keTcBHiVdIaRtig"
            },
            "snippet": {
                "publishedAt": "2020-12-25T11:15:33Z",
                "channelId": "UCFqHLi38keTcBHiVdIaRtig",
                "title": "Hello Sajeeb",
                "description": "\u0986\u09b8\u09b8\u09be\u09b2\u09be\u09ae\u09c1 \u0986\u09b2\u09be\u0987\u0995\u09c1\u09ae.",
                "thumbnails": {
                    "default": {
                        "url": "https://yt3.ggpht.com/oRfEkZ4HJh1drpQXTAwOuwlsUnk7JNE3imcWx5yD00T53tSdy1OEeV_VxZ65T-7au-J3ME3jaQ=s88-c-k-c0xffffffff-no-rj-mo"
                    },
                    "medium": {
                        "url": "https://yt3.ggpht.com/oRfEkZ4HJh1drpQXTAwOuwlsUnk7JNE3imcWx5yD00T53tSdy1OEeV_VxZ65T-7au-J3ME3jaQ=s240-c-k-c0xffffffff-no-rj-mo"
                    },
                    "high": {
                        "url": "https://yt3.ggpht.com/oRfEkZ4HJh1drpQXTAwOuwlsUnk7JNE3imcWx5yD00T53tSdy1OEeV_VxZ65T-7au-J3ME3jaQ=s800-c-k-c0xffffffff-no-rj-mo"
                    }
                },
                "channelTitle": "Hello Sajeeb",
                "liveBroadcastContent": "none",
                "publishTime": "2020-12-25T11:15:33Z"
            }
        },
        {
            "kind": "youtube#searchResult",
            "etag": "2HwGmXO24fu8FjEyZxuLVJvEzBk",
            "id": {
                "kind": "youtube#channel",
                "channelId": "UCUiFYvCOqxlsfsexmC-stSg"
            },
            "snippet": {
                "publishedAt": "2021-05-21T13:59:26Z",
                "channelId": "UCUiFYvCOqxlsfsexmC-stSg",
                "title": "HELLO ITALY BD",
                "description": "Subscribe Now My YouTube Channel \u09b8\u09be\u09ac\u09b8\u09cd\u0995\u09cd\u09b0\u09be\u0987\u09ac \u0995\u09b0\u09c1\u09a3 \u09b8\u09ac\u09be\u0987 \u0986\u09ae\u09be\u09b0 \u0987\u0989\u099f\u09bf\u0989\u09ac \u099a\u09c7\u09a8\u09c7\u09b2 ...",
                "thumbnails": {
                    "default": {
                        "url": "https://yt3.ggpht.com/o3OBP7JuAZWMSAVIN19ZFSV6ek8sLB2-_ydaDI9zgFSoYOyWdlTW25TATNCUYhCcBkept6iS2ag=s88-c-k-c0xffffffff-no-rj-mo"
                    },
                    "medium": {
                        "url": "https://yt3.ggpht.com/o3OBP7JuAZWMSAVIN19ZFSV6ek8sLB2-_ydaDI9zgFSoYOyWdlTW25TATNCUYhCcBkept6iS2ag=s240-c-k-c0xffffffff-no-rj-mo"
                    },
                    "high": {
                        "url": "https://yt3.ggpht.com/o3OBP7JuAZWMSAVIN19ZFSV6ek8sLB2-_ydaDI9zgFSoYOyWdlTW25TATNCUYhCcBkept6iS2ag=s800-c-k-c0xffffffff-no-rj-mo"
                    }
                },
                "channelTitle": "HELLO ITALY BD",
                "liveBroadcastContent": "upcoming",
                "publishTime": "2021-05-21T13:59:26Z"
            }
        },
        {
            "kind": "youtube#searchResult",
            "etag": "UBuYtiuyTSpxy11QoipTWPOCURQ",
            "id": {
                "kind": "youtube#channel",
                "channelId": "UCx4eqkB43eDawLOp96QPKZg"
            },
            "snippet": {
                "publishedAt": "2015-08-06T18:47:12Z",
                "channelId": "UCx4eqkB43eDawLOp96QPKZg",
                "title": "Hello Chittagong",
                "description": "Chittagong District is a district located in the south-eastern region of Bangladesh. It is a part of the Chittagong Division. The port ...",
                "thumbnails": {
                    "default": {
                        "url": "https://yt3.ggpht.com/ytc/AL5GRJViTCBgAmL83rTBJIAea5JrCyuvoIaDMfIY9g6FGg=s88-c-k-c0xffffffff-no-rj-mo"
                    },
                    "medium": {
                        "url": "https://yt3.ggpht.com/ytc/AL5GRJViTCBgAmL83rTBJIAea5JrCyuvoIaDMfIY9g6FGg=s240-c-k-c0xffffffff-no-rj-mo"
                    },
                    "high": {
                        "url": "https://yt3.ggpht.com/ytc/AL5GRJViTCBgAmL83rTBJIAea5JrCyuvoIaDMfIY9g6FGg=s800-c-k-c0xffffffff-no-rj-mo"
                    }
                },
                "channelTitle": "Hello Chittagong",
                "liveBroadcastContent": "upcoming",
                "publishTime": "2015-08-06T18:47:12Z"
            }
        },
        {
            "kind": "youtube#searchResult",
            "etag": "pV9qD0vLAEu-inVtA25VVJo9JN4",
            "id": {
                "kind": "youtube#channel",
                "channelId": "UCiv1FPpuU_eIsAaO9bLSErQ"
            },
            "snippet": {
                "publishedAt": "2021-05-11T13:52:43Z",
                "channelId": "UCiv1FPpuU_eIsAaO9bLSErQ",
                "title": "Hello Rajib Music",
                "description": "\u09a8\u09a4\u09c1\u09a8 \u09a8\u09a4\u09c1\u09a8 \u09ae\u09bf\u0989\u099c\u09bf\u0995 \u09ad\u09bf\u09a1\u09bf\u0993 \u09a6\u09c7\u0996\u09a4\u09c7 \u0986\u09ae\u09be\u09a6\u09c7\u09b0 \u09b8\u09be\u09a5\u09c7 \u09a5\u09be\u0995\u09c1\u09a8 \u0986\u09ae\u09b0\u09be \u0986\u09aa\u09a8\u09be\u09a6\u09c7\u09b0 \u09ad\u09be\u09b2\u09cb ...",
                "thumbnails": {
                    "default": {
                        "url": "https://yt3.ggpht.com/pDMP_xPmpBgv35msrACi-E256aBRU3afGNYsxguIyXFVx0RzREvfC4luw8K8xV9pPySPoaOm8GQ=s88-c-k-c0xffffffff-no-rj-mo"
                    },
                    "medium": {
                        "url": "https://yt3.ggpht.com/pDMP_xPmpBgv35msrACi-E256aBRU3afGNYsxguIyXFVx0RzREvfC4luw8K8xV9pPySPoaOm8GQ=s240-c-k-c0xffffffff-no-rj-mo"
                    },
                    "high": {
                        "url": "https://yt3.ggpht.com/pDMP_xPmpBgv35msrACi-E256aBRU3afGNYsxguIyXFVx0RzREvfC4luw8K8xV9pPySPoaOm8GQ=s800-c-k-c0xffffffff-no-rj-mo"
                    }
                },
                "channelTitle": "Hello Rajib Music",
                "liveBroadcastContent": "none",
                "publishTime": "2021-05-11T13:52:43Z"
            }
        },
        {
            "kind": "youtube#searchResult",
            "etag": "qin_0q93fO6ieJAlnrdiQwUdH3w",
            "id": {
                "kind": "youtube#channel",
                "channelId": "UCXYIjYyem9QeHaFv4I4nQAg"
            },
            "snippet": {
                "publishedAt": "2020-08-09T15:53:40Z",
                "channelId": "UCXYIjYyem9QeHaFv4I4nQAg",
                "title": "Hello Islam",
                "description": "Hello Islam English: As-salamu alaikum, You Can Watch Here: bangla waz, bangla mahfil, islamic lecture, jumar khutba, islamic ...",
                "thumbnails": {
                    "default": {
                        "url": "https://yt3.ggpht.com/MFPQmzbL3kCdGafc8bKVbhRXpchFyhkFVKcF8njlZq0k1Mo6-_DKN1SNtlK3L2pvOfptgDu32g=s88-c-k-c0xffffffff-no-rj-mo"
                    },
                    "medium": {
                        "url": "https://yt3.ggpht.com/MFPQmzbL3kCdGafc8bKVbhRXpchFyhkFVKcF8njlZq0k1Mo6-_DKN1SNtlK3L2pvOfptgDu32g=s240-c-k-c0xffffffff-no-rj-mo"
                    },
                    "high": {
                        "url": "https://yt3.ggpht.com/MFPQmzbL3kCdGafc8bKVbhRXpchFyhkFVKcF8njlZq0k1Mo6-_DKN1SNtlK3L2pvOfptgDu32g=s800-c-k-c0xffffffff-no-rj-mo"
                    }
                },
                "channelTitle": "Hello Islam",
                "liveBroadcastContent": "none",
                "publishTime": "2020-08-09T15:53:40Z"
            }
        },
        {
            "kind": "youtube#searchResult",
            "etag": "ZsheVT7X7Rlfd7XeBBaeZdp0sw4",
            "id": {
                "kind": "youtube#channel",
                "channelId": "UCYFqXGZZxPywATqu7kv0TMQ"
            },
            "snippet": {
                "publishedAt": "2020-06-05T21:46:24Z",
                "channelId": "UCYFqXGZZxPywATqu7kv0TMQ",
                "title": "Hello Momin",
                "description": "https://www.youtube.com/feed/my_videos.",
                "thumbnails": {
                    "default": {
                        "url": "https://yt3.ggpht.com/ytc/AL5GRJVpdizJBjNqIb7_IR4SaevGp7eYgK3aKt1oDydx=s88-c-k-c0xffffffff-no-rj-mo"
                    },
                    "medium": {
                        "url": "https://yt3.ggpht.com/ytc/AL5GRJVpdizJBjNqIb7_IR4SaevGp7eYgK3aKt1oDydx=s240-c-k-c0xffffffff-no-rj-mo"
                    },
                    "high": {
                        "url": "https://yt3.ggpht.com/ytc/AL5GRJVpdizJBjNqIb7_IR4SaevGp7eYgK3aKt1oDydx=s800-c-k-c0xffffffff-no-rj-mo"
                    }
                },
                "channelTitle": "Hello Momin",
                "liveBroadcastContent": "none",
                "publishTime": "2020-06-05T21:46:24Z"
            }
        },
        {
            "kind": "youtube#searchResult",
            "etag": "6xSvXZKzgP3wJ6vrn9_Ue5-G-UU",
            "id": {
                "kind": "youtube#channel",
                "channelId": "UC8lnmTA5u9sfqbHtDeNClAQ"
            },
            "snippet": {
                "publishedAt": "2018-10-22T13:49:40Z",
                "channelId": "UC8lnmTA5u9sfqbHtDeNClAQ",
                "title": "Hello Origami",
                "description": "\u041f\u0440\u0438\u0432\u0435\u0442! \u041c\u0435\u043d\u044f \u0437\u043e\u0432\u0443\u0442 \u0410\u043b\u0438\u0441\u0430 \u0438 \u043d\u0430 \u043c\u043e\u0435\u043c \u043a\u0430\u043d\u0430\u043b\u0435 \u043c\u044b \u0441\u043e\u0431\u0438\u0440\u0430\u0435\u043c \u043e\u0440\u0438\u0433\u0430\u043c\u0438: \u0437\u0430\u043a\u043b\u0430\u0434\u043a\u0438, \u043a\u043e\u0440\u043e\u0431\u043e\u0447\u043a\u0438, \u043e\u0442\u043a\u0440\u044b\u0442\u043a\u0438 \u043c\u0438\u043b\u044b\u0445 \u0436\u0438\u0432\u043e\u0442\u043d\u044b\u0445 \u0438 ...",
                "thumbnails": {
                    "default": {
                        "url": "https://yt3.ggpht.com/ytc/AL5GRJXXPtu7d7YxgUxcMyYEh6sU1x3lPJIhzrUyoEO-og=s88-c-k-c0xffffffff-no-rj-mo"
                    },
                    "medium": {
                        "url": "https://yt3.ggpht.com/ytc/AL5GRJXXPtu7d7YxgUxcMyYEh6sU1x3lPJIhzrUyoEO-og=s240-c-k-c0xffffffff-no-rj-mo"
                    },
                    "high": {
                        "url": "https://yt3.ggpht.com/ytc/AL5GRJXXPtu7d7YxgUxcMyYEh6sU1x3lPJIhzrUyoEO-og=s800-c-k-c0xffffffff-no-rj-mo"
                    }
                },
                "channelTitle": "Hello Origami",
                "liveBroadcastContent": "none",
                "publishTime": "2018-10-22T13:49:40Z"
            }
        },
        {
            "kind": "youtube#searchResult",
            "etag": "i3Vg_p7W7GoO1x-Wg8Spra39bWY",
            "id": {
                "kind": "youtube#channel",
                "channelId": "UC3IaQUoGz7JEmFPHP7xec6Q"
            },
            "snippet": {
                "publishedAt": "2019-09-12T14:36:56Z",
                "channelId": "UC3IaQUoGz7JEmFPHP7xec6Q",
                "title": "Hello Sylhet bd",
                "description": "\u0986\u09b8\u09c1\u09a8 \u09aa\u09b0\u09bf\u09ac\u09b0\u09cd\u09a4\u09a8\u099f\u09be \u0986\u0997\u09c7 \u09a8\u09bf\u099c\u09c7 \u09a5\u09c7\u0995\u09c7\u0987 \u0986\u09a8\u09bf\u2764\u0986\u09ae\u09b0\u09be \u0986\u09ae\u09be\u09a6\u09c7\u09b0 \u09b8\u09be\u09a7\u09cd\u09af\u09ae\u09a4\u09cb \u099a\u09c7\u09b7\u09cd\u099f\u09be ...",
                "thumbnails": {
                    "default": {
                        "url": "https://yt3.ggpht.com/ytc/AL5GRJVUj3jCA0cx2JoaP-ijDMuIEoxNDAQ46XxIwaiHRQ=s88-c-k-c0xffffffff-no-rj-mo"
                    },
                    "medium": {
                        "url": "https://yt3.ggpht.com/ytc/AL5GRJVUj3jCA0cx2JoaP-ijDMuIEoxNDAQ46XxIwaiHRQ=s240-c-k-c0xffffffff-no-rj-mo"
                    },
                    "high": {
                        "url": "https://yt3.ggpht.com/ytc/AL5GRJVUj3jCA0cx2JoaP-ijDMuIEoxNDAQ46XxIwaiHRQ=s800-c-k-c0xffffffff-no-rj-mo"
                    }
                },
                "channelTitle": "Hello Sylhet bd",
                "liveBroadcastContent": "none",
                "publishTime": "2019-09-12T14:36:56Z"
            }
        },
        {
            "kind": "youtube#searchResult",
            "etag": "6_WmmXal5f7uhVmU0iPadP9SnpY",
            "id": {
                "kind": "youtube#channel",
                "channelId": "UCtfeIrLl2i7DvswAF3DL2wg"
            },
            "snippet": {
                "publishedAt": "2022-08-28T15:18:58Z",
                "channelId": "UCtfeIrLl2i7DvswAF3DL2wg",
                "title": "Hello Sir (Wasif Rustom)",
                "description": "\u0986\u09b8\u09b8\u09be\u09b2\u09be\u09ae\u09c1 \u0986\u09b2\u09be\u0987\u0995\u09c1\u09ae \u09b8\u09ac\u09be\u0987\u0995\u09c7\u0964 \u0986\u09ae\u09bf \u0993\u09af\u09bc\u09be\u09b8\u09bf\u09ab \u09b0\u09c1\u09b8\u09cd\u09a4\u09ae (\u09ac\u09bf.\u098f\u09b8\u09b8\u09bf.\u0985\u09a8\u09be\u09b0\u09cd\u09b8,\u098f\u09ae.",
                "thumbnails": {
                    "default": {
                        "url": "https://yt3.ggpht.com/tzkir29HtxDuroDARc0mDyAPYqAhWBl1GMDQW2FXklFkiUdE4NKxWi5tzB7nHA9HGNhRAGnCBg=s88-c-k-c0xffffffff-no-rj-mo"
                    },
                    "medium": {
                        "url": "https://yt3.ggpht.com/tzkir29HtxDuroDARc0mDyAPYqAhWBl1GMDQW2FXklFkiUdE4NKxWi5tzB7nHA9HGNhRAGnCBg=s240-c-k-c0xffffffff-no-rj-mo"
                    },
                    "high": {
                        "url": "https://yt3.ggpht.com/tzkir29HtxDuroDARc0mDyAPYqAhWBl1GMDQW2FXklFkiUdE4NKxWi5tzB7nHA9HGNhRAGnCBg=s800-c-k-c0xffffffff-no-rj-mo"
                    }
                },
                "channelTitle": "Hello Sir (Wasif Rustom)",
                "liveBroadcastContent": "none",
                "publishTime": "2022-08-28T15:18:58Z"
            }
        },
        {
            "kind": "youtube#searchResult",
            "etag": "npn5QI3KUHCVP4EZGJLjU-yYSYY",
            "id": {
                "kind": "youtube#channel",
                "channelId": "UCShQlskXG5e7keyPHDlcgQA"
            },
            "snippet": {
                "publishedAt": "2021-03-02T10:38:10Z",
                "channelId": "UCShQlskXG5e7keyPHDlcgQA",
                "title": "Hello mobile care",
                "description": "\u09ae\u09cb\u09ac\u09be\u0987\u09b2 \u09ab\u09cb\u09a8 \u099c\u0997\u09a4\u09c7\u09b0 \u09b8\u0995\u09b2 \u09b8\u09ae\u09be\u09a7\u09be\u09a8\u0964 All the solutions in the mobile phone world.",
                "thumbnails": {
                    "default": {
                        "url": "https://yt3.ggpht.com/ytc/AL5GRJUM4hqfNWso3AwijJACqpuj1BebXxbq5QgCVfFP=s88-c-k-c0xffffffff-no-rj-mo"
                    },
                    "medium": {
                        "url": "https://yt3.ggpht.com/ytc/AL5GRJUM4hqfNWso3AwijJACqpuj1BebXxbq5QgCVfFP=s240-c-k-c0xffffffff-no-rj-mo"
                    },
                    "high": {
                        "url": "https://yt3.ggpht.com/ytc/AL5GRJUM4hqfNWso3AwijJACqpuj1BebXxbq5QgCVfFP=s800-c-k-c0xffffffff-no-rj-mo"
                    }
                },
                "channelTitle": "Hello mobile care",
                "liveBroadcastContent": "none",
                "publishTime": "2021-03-02T10:38:10Z"
            }
        },
        {
            "kind": "youtube#searchResult",
            "etag": "CHzGY7-5mcUCQiyN2EqDsdJkVvg",
            "id": {
                "kind": "youtube#channel",
                "channelId": "UC14TZOhetUHELrt-SSxQzQA"
            },
            "snippet": {
                "publishedAt": "2022-01-13T12:49:00Z",
                "channelId": "UC14TZOhetUHELrt-SSxQzQA",
                "title": "Hello Village BD",
                "description": "\u0997\u09cd\u09b0\u09be\u09ae\u09c7\u09b0 \u099b\u09c7\u09b2\u09c7 \u09ae\u09c7\u09af\u09bc\u09c7\u09a6\u09c7\u09b0 \u09a8\u09bf\u09af\u09bc\u09c7 \u09ae\u099c\u09be\u09b0 \u09ae\u099c\u09be\u09b0 \u09ad\u09bf\u09a1\u09bf\u0993 \u09a6\u09c7\u0987\u0964 \u09a6\u09b0\u09cd\u09b6\u0995 \u0986\u09aa\u09a8\u09be\u09b0 ...",
                "thumbnails": {
                    "default": {
                        "url": "https://yt3.ggpht.com/sXt0rz6tNwxRzD0ftjdlDX-fVByELjN08ykZ4NG8-xCcHhuIwnfnUhLN1DWrc4zBEwZPbOWe=s88-c-k-c0xffffffff-no-rj-mo"
                    },
                    "medium": {
                        "url": "https://yt3.ggpht.com/sXt0rz6tNwxRzD0ftjdlDX-fVByELjN08ykZ4NG8-xCcHhuIwnfnUhLN1DWrc4zBEwZPbOWe=s240-c-k-c0xffffffff-no-rj-mo"
                    },
                    "high": {
                        "url": "https://yt3.ggpht.com/sXt0rz6tNwxRzD0ftjdlDX-fVByELjN08ykZ4NG8-xCcHhuIwnfnUhLN1DWrc4zBEwZPbOWe=s800-c-k-c0xffffffff-no-rj-mo"
                    }
                },
                "channelTitle": "Hello Village BD",
                "liveBroadcastContent": "none",
                "publishTime": "2022-01-13T12:49:00Z"
            }
        },
        {
            "kind": "youtube#searchResult",
            "etag": "k3kzjrjcO_eNaSV7Fvpoi6Wjqpc",
            "id": {
                "kind": "youtube#channel",
                "channelId": "UC4-n8sh5bw-_xBVgKwCxz-Q"
            },
            "snippet": {
                "publishedAt": "2021-11-29T09:31:08Z",
                "channelId": "UC4-n8sh5bw-_xBVgKwCxz-Q",
                "title": "Hello HSC",
                "description": "welcome to hello HSC. this is a HSC and admission based channel. We are going to teach and motivate you to bright your life.",
                "thumbnails": {
                    "default": {
                        "url": "https://yt3.ggpht.com/9ZxH6tAJAJwqeIcbR3MIPebwy3kgr2qSM7h_zRNfU6w7iFzXptCz8Ofp7hsra-fZkCREjKVU=s88-c-k-c0xffffffff-no-rj-mo"
                    },
                    "medium": {
                        "url": "https://yt3.ggpht.com/9ZxH6tAJAJwqeIcbR3MIPebwy3kgr2qSM7h_zRNfU6w7iFzXptCz8Ofp7hsra-fZkCREjKVU=s240-c-k-c0xffffffff-no-rj-mo"
                    },
                    "high": {
                        "url": "https://yt3.ggpht.com/9ZxH6tAJAJwqeIcbR3MIPebwy3kgr2qSM7h_zRNfU6w7iFzXptCz8Ofp7hsra-fZkCREjKVU=s800-c-k-c0xffffffff-no-rj-mo"
                    }
                },
                "channelTitle": "Hello HSC",
                "liveBroadcastContent": "upcoming",
                "publishTime": "2021-11-29T09:31:08Z"
            }
        },
        {
            "kind": "youtube#searchResult",
            "etag": "jzBQaZuXGTRVgOL47uf5HWG9Pbk",
            "id": {
                "kind": "youtube#channel",
                "channelId": "UCGH-Gl8WAmgGdXngnyBl6Ow"
            },
            "snippet": {
                "publishedAt": "2021-04-27T04:43:21Z",
                "channelId": "UCGH-Gl8WAmgGdXngnyBl6Ow",
                "title": "Hello Vehicle",
                "description": "",
                "thumbnails": {
                    "default": {
                        "url": "https://yt3.ggpht.com/ytc/AL5GRJVqHhH0IoPyjiSjzP2tNncgXvNMS1QvRZFU9vak=s88-c-k-c0xffffffff-no-rj-mo"
                    },
                    "medium": {
                        "url": "https://yt3.ggpht.com/ytc/AL5GRJVqHhH0IoPyjiSjzP2tNncgXvNMS1QvRZFU9vak=s240-c-k-c0xffffffff-no-rj-mo"
                    },
                    "high": {
                        "url": "https://yt3.ggpht.com/ytc/AL5GRJVqHhH0IoPyjiSjzP2tNncgXvNMS1QvRZFU9vak=s800-c-k-c0xffffffff-no-rj-mo"
                    }
                },
                "channelTitle": "Hello Vehicle",
                "liveBroadcastContent": "none",
                "publishTime": "2021-04-27T04:43:21Z"
            }
        },
        {
            "kind": "youtube#searchResult",
            "etag": "C-tNCXkfnE9wEOq48Ttn-QCPvNs",
            "id": {
                "kind": "youtube#channel",
                "channelId": "UCA6-gHeTHvE-ekXZO06eVpg"
            },
            "snippet": {
                "publishedAt": "2022-06-13T18:20:39Z",
                "channelId": "UCA6-gHeTHvE-ekXZO06eVpg",
                "title": "Hello Bogura Farhad",
                "description": "Welcome to. Hello bogura Farhad Md Farhad Hasan of Bogura adda Bogura network Bogura adda new Bogura adda official ...",
                "thumbnails": {
                    "default": {
                        "url": "https://yt3.ggpht.com/P7gvs8I6nocpyjRR9qDxycp9vXc1HtbM5q0_0pfqjYkSUCCoKBcqm42JVBgV200IjQkp6V3sZHI=s88-c-k-c0xffffffff-no-rj-mo"
                    },
                    "medium": {
                        "url": "https://yt3.ggpht.com/P7gvs8I6nocpyjRR9qDxycp9vXc1HtbM5q0_0pfqjYkSUCCoKBcqm42JVBgV200IjQkp6V3sZHI=s240-c-k-c0xffffffff-no-rj-mo"
                    },
                    "high": {
                        "url": "https://yt3.ggpht.com/P7gvs8I6nocpyjRR9qDxycp9vXc1HtbM5q0_0pfqjYkSUCCoKBcqm42JVBgV200IjQkp6V3sZHI=s800-c-k-c0xffffffff-no-rj-mo"
                    }
                },
                "channelTitle": "Hello Bogura Farhad",
                "liveBroadcastContent": "none",
                "publishTime": "2022-06-13T18:20:39Z"
            }
        },
        {
            "kind": "youtube#searchResult",
            "etag": "TaFx1NFTtfKM4uK6l0LL_BYn8UY",
            "id": {
                "kind": "youtube#channel",
                "channelId": "UCs7vDJki1DxS_3fpEnd81aw"
            },
            "snippet": {
                "publishedAt": "2021-10-06T06:17:31Z",
                "channelId": "UCs7vDJki1DxS_3fpEnd81aw",
                "title": "Gaming Hello",
                "description": "gaming video and evrything MY GOAL 5K SUBSCRIBERS Subscribe Comment Share Like THANK YOU EVERYONE \u2763\ufe0f My ...",
                "thumbnails": {
                    "default": {
                        "url": "https://yt3.ggpht.com/mXftcxFb-TPsVgUmvy5Eyjz6uW44vmIwoSA0QJRQFNIlWBnYnzKrQKD-zXW0fnUasbUufRh6=s88-c-k-c0xffffffff-no-rj-mo"
                    },
                    "medium": {
                        "url": "https://yt3.ggpht.com/mXftcxFb-TPsVgUmvy5Eyjz6uW44vmIwoSA0QJRQFNIlWBnYnzKrQKD-zXW0fnUasbUufRh6=s240-c-k-c0xffffffff-no-rj-mo"
                    },
                    "high": {
                        "url": "https://yt3.ggpht.com/mXftcxFb-TPsVgUmvy5Eyjz6uW44vmIwoSA0QJRQFNIlWBnYnzKrQKD-zXW0fnUasbUufRh6=s800-c-k-c0xffffffff-no-rj-mo"
                    }
                },
                "channelTitle": "Gaming Hello",
                "liveBroadcastContent": "upcoming",
                "publishTime": "2021-10-06T06:17:31Z"
            }
        },
        {
            "kind": "youtube#searchResult",
            "etag": "Dm7pclJcafcbaI7chQtsGS0elIE",
            "id": {
                "kind": "youtube#channel",
                "channelId": "UCEp-ygzilyp7V-ZwR40xY9w"
            },
            "snippet": {
                "publishedAt": "2020-12-02T03:31:34Z",
                "channelId": "UCEp-ygzilyp7V-ZwR40xY9w",
                "title": "Hello Europe 2020",
                "description": "\u0987\u0989\u09b0\u09cb\u09aa \u0993 \u09ac\u09be\u0982\u09b2\u09be\u09a6\u09c7\u09b6\u09c7\u09b0 \u09b8\u0995\u09b2 \u09aa\u09cd\u09b0\u0995\u09be\u09b0 \u0997\u09c1\u09b0\u09c1\u09a4\u09cd\u09ac\u09aa\u09c2\u09b0\u09cd\u09a3 \u0996\u09ac\u09b0\u09be \u0996\u09ac\u09b0 \u09b8\u09ac\u09be\u09b0 \u0986\u0997\u09c7 \u09aa\u09c7\u09a4\u09c7 ...",
                "thumbnails": {
                    "default": {
                        "url": "https://yt3.ggpht.com/ytc/AL5GRJWgcNHtJy3LYsj-aUOCz7fNjrED2MXR11cKgI53=s88-c-k-c0xffffffff-no-rj-mo"
                    },
                    "medium": {
                        "url": "https://yt3.ggpht.com/ytc/AL5GRJWgcNHtJy3LYsj-aUOCz7fNjrED2MXR11cKgI53=s240-c-k-c0xffffffff-no-rj-mo"
                    },
                    "high": {
                        "url": "https://yt3.ggpht.com/ytc/AL5GRJWgcNHtJy3LYsj-aUOCz7fNjrED2MXR11cKgI53=s800-c-k-c0xffffffff-no-rj-mo"
                    }
                },
                "channelTitle": "Hello Europe 2020",
                "liveBroadcastContent": "none",
                "publishTime": "2020-12-02T03:31:34Z"
            }
        },
        {
            "kind": "youtube#searchResult",
            "etag": "mpdhRvVHv3bBolYbDLAdOnZBPPw",
            "id": {
                "kind": "youtube#channel",
                "channelId": "UChy_1qZLjj_VeLDdb2TzdgA"
            },
            "snippet": {
                "publishedAt": "2017-06-28T18:15:01Z",
                "channelId": "UChy_1qZLjj_VeLDdb2TzdgA",
                "title": "Hello Shifat",
                "description": "HELLO SHIFAT Mobile Repairing Training Center Brahmanbaria Bangladesh \u09b9\u09cd\u09af\u09be\u09b2\u09cb \u09b8\u09bf\u09ab\u09be\u09a4 \u09ae\u09cb\u09ac\u09be\u0987\u09b2 ...",
                "thumbnails": {
                    "default": {
                        "url": "https://yt3.ggpht.com/ytc/AL5GRJU_24di3gygz4-2hpH7GArMyU2T1Ew9K4rzZCMIbQ=s88-c-k-c0xffffffff-no-rj-mo"
                    },
                    "medium": {
                        "url": "https://yt3.ggpht.com/ytc/AL5GRJU_24di3gygz4-2hpH7GArMyU2T1Ew9K4rzZCMIbQ=s240-c-k-c0xffffffff-no-rj-mo"
                    },
                    "high": {
                        "url": "https://yt3.ggpht.com/ytc/AL5GRJU_24di3gygz4-2hpH7GArMyU2T1Ew9K4rzZCMIbQ=s800-c-k-c0xffffffff-no-rj-mo"
                    }
                },
                "channelTitle": "Hello Shifat",
                "liveBroadcastContent": "upcoming",
                "publishTime": "2017-06-28T18:15:01Z"
            }
        },
        {
            "kind": "youtube#searchResult",
            "etag": "4GpJpPsjO1p7FGL8CEo6-O93AX4",
            "id": {
                "kind": "youtube#channel",
                "channelId": "UCugoxKJyOmopgktsrScIPGw"
            },
            "snippet": {
                "publishedAt": "2014-02-22T17:09:14Z",
                "channelId": "UCugoxKJyOmopgktsrScIPGw",
                "title": "hello Rasel",
                "description": "\u09b8\u09b9\u09af\u09cb\u0997\u09bf\u09a4\u09be \u099c\u09a8\u09cd\u09af \u0986\u09ae\u09bf \u0986\u09aa\u09a8\u09be\u09a6\u09c7\u09b0 \u09aa\u09be\u09b6\u09c7 \u09a5\u09be\u0995\u09ac\u09cb.",
                "thumbnails": {
                    "default": {
                        "url": "https://yt3.ggpht.com/0FKshBOsXNbbYon6jAp3tgq0FoucfpYa8oZNUmvW5OJJcmQZ7YMvFAQbLR93pvikFI51SX8ZLg=s88-c-k-c0xffffffff-no-rj-mo"
                    },
                    "medium": {
                        "url": "https://yt3.ggpht.com/0FKshBOsXNbbYon6jAp3tgq0FoucfpYa8oZNUmvW5OJJcmQZ7YMvFAQbLR93pvikFI51SX8ZLg=s240-c-k-c0xffffffff-no-rj-mo"
                    },
                    "high": {
                        "url": "https://yt3.ggpht.com/0FKshBOsXNbbYon6jAp3tgq0FoucfpYa8oZNUmvW5OJJcmQZ7YMvFAQbLR93pvikFI51SX8ZLg=s800-c-k-c0xffffffff-no-rj-mo"
                    }
                },
                "channelTitle": "hello Rasel",
                "liveBroadcastContent": "upcoming",
                "publishTime": "2014-02-22T17:09:14Z"
            }
        },
        {
            "kind": "youtube#searchResult",
            "etag": "QrRto1tEQR8jdb6SEfYVm5htp0Q",
            "id": {
                "kind": "youtube#channel",
                "channelId": "UCT56EexMItrAj0zAjfonAEg"
            },
            "snippet": {
                "publishedAt": "2019-10-20T07:30:48Z",
                "channelId": "UCT56EexMItrAj0zAjfonAEg",
                "title": "Hello Hello",
                "description": "\u5948\u826f\u770c\u767a3\u30d4\u30fc\u30b9\u30ed\u30c3\u30af\u30d0\u30f3\u30c9.",
                "thumbnails": {
                    "default": {
                        "url": "https://yt3.ggpht.com/WhKI5ZEBkVqN6c0c_qXi6SMFm-VbQCv6v-64VCsPiImbwUIc_Z84TaAbZWWXH0U2QFWgDjmxgpw=s88-c-k-c0xffffffff-no-rj-mo"
                    },
                    "medium": {
                        "url": "https://yt3.ggpht.com/WhKI5ZEBkVqN6c0c_qXi6SMFm-VbQCv6v-64VCsPiImbwUIc_Z84TaAbZWWXH0U2QFWgDjmxgpw=s240-c-k-c0xffffffff-no-rj-mo"
                    },
                    "high": {
                        "url": "https://yt3.ggpht.com/WhKI5ZEBkVqN6c0c_qXi6SMFm-VbQCv6v-64VCsPiImbwUIc_Z84TaAbZWWXH0U2QFWgDjmxgpw=s800-c-k-c0xffffffff-no-rj-mo"
                    }
                },
                "channelTitle": "Hello Hello",
                "liveBroadcastContent": "none",
                "publishTime": "2019-10-20T07:30:48Z"
            }
        },
        {
            "kind": "youtube#searchResult",
            "etag": "JPK7XrWaLl7lYQ2EN82OG5MLZEY",
            "id": {
                "kind": "youtube#channel",
                "channelId": "UC_FWU9rldW1hWvA_DPKPZZw"
            },
            "snippet": {
                "publishedAt": "2022-09-01T05:20:27Z",
                "channelId": "UC_FWU9rldW1hWvA_DPKPZZw",
                "title": "Hello Bangladesh 1234",
                "description": "Hello Bangladesh 1234 hello bangladesh 1234 @hello #bangladesh #1234 Bangladesh hello Bangladesh hello Bangladesh ...",
                "thumbnails": {
                    "default": {
                        "url": "https://yt3.ggpht.com/dYEoaakSf7YVNm2z-s4uF_3qBB3Oq-H2gKqgU0KOw2YMcvUyquTR_u_Y7c4cf9bUTi8sL1Rj=s88-c-k-c0xffffffff-no-rj-mo"
                    },
                    "medium": {
                        "url": "https://yt3.ggpht.com/dYEoaakSf7YVNm2z-s4uF_3qBB3Oq-H2gKqgU0KOw2YMcvUyquTR_u_Y7c4cf9bUTi8sL1Rj=s240-c-k-c0xffffffff-no-rj-mo"
                    },
                    "high": {
                        "url": "https://yt3.ggpht.com/dYEoaakSf7YVNm2z-s4uF_3qBB3Oq-H2gKqgU0KOw2YMcvUyquTR_u_Y7c4cf9bUTi8sL1Rj=s800-c-k-c0xffffffff-no-rj-mo"
                    }
                },
                "channelTitle": "Hello Bangladesh 1234",
                "liveBroadcastContent": "none",
                "publishTime": "2022-09-01T05:20:27Z"
            }
        },
        {
            "kind": "youtube#searchResult",
            "etag": "eye4DFJPZvNNEutmyYc2G61BSlw",
            "id": {
                "kind": "youtube#channel",
                "channelId": "UCNWnfhlkxTsVwZDtMSmX8ug"
            },
            "snippet": {
                "publishedAt": "2020-04-09T01:29:31Z",
                "channelId": "UCNWnfhlkxTsVwZDtMSmX8ug",
                "title": "Hello America",
                "description": "\u0995\u09bf \u09a5\u09be\u0995\u09ac\u09c7 \u098f\u0987 \u099a\u09cd\u09af\u09be\u09a8\u09c7\u09b2\u09c7? \u09e7\u0964 \u0986\u09ae\u09c7\u09b0\u09bf\u0995\u09be\u09a4\u09c7 \u0986\u09aa\u09a8\u09be\u09b0\u09be \u0995\u09bf\u09ad\u09be\u09ac\u09c7 \u0986\u09b8\u09ac\u09c7\u09a8? \u098f\u09b8\u09ac ...",
                "thumbnails": {
                    "default": {
                        "url": "https://yt3.ggpht.com/ytc/AL5GRJXVgZIqLGwRcrBfS4ZMT9mpO5omIlc1W79AHAMT0Q=s88-c-k-c0xffffffff-no-rj-mo"
                    },
                    "medium": {
                        "url": "https://yt3.ggpht.com/ytc/AL5GRJXVgZIqLGwRcrBfS4ZMT9mpO5omIlc1W79AHAMT0Q=s240-c-k-c0xffffffff-no-rj-mo"
                    },
                    "high": {
                        "url": "https://yt3.ggpht.com/ytc/AL5GRJXVgZIqLGwRcrBfS4ZMT9mpO5omIlc1W79AHAMT0Q=s800-c-k-c0xffffffff-no-rj-mo"
                    }
                },
                "channelTitle": "Hello America",
                "liveBroadcastContent": "none",
                "publishTime": "2020-04-09T01:29:31Z"
            }
        },
        {
            "kind": "youtube#searchResult",
            "etag": "rmuMFFEQUGQj3dcL7EEzigXJxVo",
            "id": {
                "kind": "youtube#channel",
                "channelId": "UCj3SjSx1fvpmxdv4aYrjZdQ"
            },
            "snippet": {
                "publishedAt": "2020-04-28T18:24:03Z",
                "channelId": "UCj3SjSx1fvpmxdv4aYrjZdQ",
                "title": "Hello Rajshahi",
                "description": "",
                "thumbnails": {
                    "default": {
                        "url": "https://yt3.ggpht.com/DJq_MO0GeRm78VFuQrs3URYKOWORbgwXkgXagktbK4X65QJqom4v0D4HRzr3lnwdsFTQB0Zn=s88-c-k-c0xffffffff-no-rj-mo"
                    },
                    "medium": {
                        "url": "https://yt3.ggpht.com/DJq_MO0GeRm78VFuQrs3URYKOWORbgwXkgXagktbK4X65QJqom4v0D4HRzr3lnwdsFTQB0Zn=s240-c-k-c0xffffffff-no-rj-mo"
                    },
                    "high": {
                        "url": "https://yt3.ggpht.com/DJq_MO0GeRm78VFuQrs3URYKOWORbgwXkgXagktbK4X65QJqom4v0D4HRzr3lnwdsFTQB0Zn=s800-c-k-c0xffffffff-no-rj-mo"
                    }
                },
                "channelTitle": "Hello Rajshahi",
                "liveBroadcastContent": "none",
                "publishTime": "2020-04-28T18:24:03Z"
            }
        },
        {
            "kind": "youtube#searchResult",
            "etag": "2TdbLGoQCPRSVdbSQGjEFXWX4Hc",
            "id": {
                "kind": "youtube#channel",
                "channelId": "UC0VyutIuYrW09BbwLCGLJsQ"
            },
            "snippet": {
                "publishedAt": "2022-08-10T15:51:33Z",
                "channelId": "UC0VyutIuYrW09BbwLCGLJsQ",
                "title": "Hello China",
                "description": "This Channel is especially for Motovlog lovers, tourism lovers, food lovers, especially Chinese culture, Dancing, Chinese food, ...",
                "thumbnails": {
                    "default": {
                        "url": "https://yt3.ggpht.com/Xbm49zcHzdpvMX7f5VOpsYzjYlP3KEV1OodsrKXk_oxw6thtODwF0vDa48JFZvgYp6iZPC-cTA=s88-c-k-c0xffffffff-no-rj-mo"
                    },
                    "medium": {
                        "url": "https://yt3.ggpht.com/Xbm49zcHzdpvMX7f5VOpsYzjYlP3KEV1OodsrKXk_oxw6thtODwF0vDa48JFZvgYp6iZPC-cTA=s240-c-k-c0xffffffff-no-rj-mo"
                    },
                    "high": {
                        "url": "https://yt3.ggpht.com/Xbm49zcHzdpvMX7f5VOpsYzjYlP3KEV1OodsrKXk_oxw6thtODwF0vDa48JFZvgYp6iZPC-cTA=s800-c-k-c0xffffffff-no-rj-mo"
                    }
                },
                "channelTitle": "Hello China",
                "liveBroadcastContent": "none",
                "publishTime": "2022-08-10T15:51:33Z"
            }
        },
        {
            "kind": "youtube#searchResult",
            "etag": "4J9IvEcNyhGkoV3DGeK3ckyrCzA",
            "id": {
                "kind": "youtube#channel",
                "channelId": "UCqhsV7sfzsQyAAifc30iqgw"
            },
            "snippet": {
                "publishedAt": "2021-01-09T04:55:35Z",
                "channelId": "UCqhsV7sfzsQyAAifc30iqgw",
                "title": "Hello from leena",
                "description": "Hi everyone!   Welcome to my channel. I'm Leena and I am a university student from Bangladesh. In this channel you can watch ...",
                "thumbnails": {
                    "default": {
                        "url": "https://yt3.ggpht.com/GyiSkevyS65lBLiSrgRDxmFJnY4a3r_TZFPZ5AdZd9poBJFgJ-FxKihyRV_pBBw8GXAAqt9g=s88-c-k-c0xffffffff-no-rj-mo"
                    },
                    "medium": {
                        "url": "https://yt3.ggpht.com/GyiSkevyS65lBLiSrgRDxmFJnY4a3r_TZFPZ5AdZd9poBJFgJ-FxKihyRV_pBBw8GXAAqt9g=s240-c-k-c0xffffffff-no-rj-mo"
                    },
                    "high": {
                        "url": "https://yt3.ggpht.com/GyiSkevyS65lBLiSrgRDxmFJnY4a3r_TZFPZ5AdZd9poBJFgJ-FxKihyRV_pBBw8GXAAqt9g=s800-c-k-c0xffffffff-no-rj-mo"
                    }
                },
                "channelTitle": "Hello from leena",
                "liveBroadcastContent": "none",
                "publishTime": "2021-01-09T04:55:35Z"
            }
        },
        {
            "kind": "youtube#searchResult",
            "etag": "D5Pluj9BnSNF8N8kRMkV2AaghVY",
            "id": {
                "kind": "youtube#channel",
                "channelId": "UCWpw6F0bRBVpcHx3okA8zyQ"
            },
            "snippet": {
                "publishedAt": "2018-10-31T11:04:47Z",
                "channelId": "UCWpw6F0bRBVpcHx3okA8zyQ",
                "title": "HELLO GSM",
                "description": "This channel offers support for solving all types of mobile hardware and softwares. Subscribe to the channel to get updated news ...",
                "thumbnails": {
                    "default": {
                        "url": "https://yt3.ggpht.com/ytc/AL5GRJVbC3XrGVJUmB0vvo2FSKQttMir4d8whNLZDui5=s88-c-k-c0xffffffff-no-rj-mo"
                    },
                    "medium": {
                        "url": "https://yt3.ggpht.com/ytc/AL5GRJVbC3XrGVJUmB0vvo2FSKQttMir4d8whNLZDui5=s240-c-k-c0xffffffff-no-rj-mo"
                    },
                    "high": {
                        "url": "https://yt3.ggpht.com/ytc/AL5GRJVbC3XrGVJUmB0vvo2FSKQttMir4d8whNLZDui5=s800-c-k-c0xffffffff-no-rj-mo"
                    }
                },
                "channelTitle": "HELLO GSM",
                "liveBroadcastContent": "none",
                "publishTime": "2018-10-31T11:04:47Z"
            }
        },
        {
            "kind": "youtube#searchResult",
            "etag": "wTweN6OE0rdMR9srSLE0_0Q4w8U",
            "id": {
                "kind": "youtube#channel",
                "channelId": "UChOwMTC_rolzQ4rTGOMeNWA"
            },
            "snippet": {
                "publishedAt": "2009-05-25T17:55:53Z",
                "channelId": "UChOwMTC_rolzQ4rTGOMeNWA",
                "title": "Hello Jewel",
                "description": "A Bangladeshi Content Creator, Working as a Journalist in Visual TV Media. I am now working on many development project of ...",
                "thumbnails": {
                    "default": {
                        "url": "https://yt3.ggpht.com/FPWulijdlnKwI0Jz7fGBksPAs03v0fYvPuDiwNtjyERjQzSZ3crgNVAibipoPFEpe1iDzxOh3A=s88-c-k-c0xffffffff-no-rj-mo"
                    },
                    "medium": {
                        "url": "https://yt3.ggpht.com/FPWulijdlnKwI0Jz7fGBksPAs03v0fYvPuDiwNtjyERjQzSZ3crgNVAibipoPFEpe1iDzxOh3A=s240-c-k-c0xffffffff-no-rj-mo"
                    },
                    "high": {
                        "url": "https://yt3.ggpht.com/FPWulijdlnKwI0Jz7fGBksPAs03v0fYvPuDiwNtjyERjQzSZ3crgNVAibipoPFEpe1iDzxOh3A=s800-c-k-c0xffffffff-no-rj-mo"
                    }
                },
                "channelTitle": "Hello Jewel",
                "liveBroadcastContent": "upcoming",
                "publishTime": "2009-05-25T17:55:53Z"
            }
        },
        {
            "kind": "youtube#searchResult",
            "etag": "QH6tvz_84scoZy7FIWfqbfvrdYA",
            "id": {
                "kind": "youtube#channel",
                "channelId": "UCIttIZCQ9IC57dTsMXoM_RA"
            },
            "snippet": {
                "publishedAt": "2019-08-31T15:52:46Z",
                "channelId": "UCIttIZCQ9IC57dTsMXoM_RA",
                "title": "Hello Romania",
                "description": "\u09aa\u09c3\u09a5\u09bf\u09ac\u09c0\u09b0 \u09a8\u09be\u09a8\u09be \u09b8\u09cd\u09a5\u09be\u09a8\u09c7 \u099b\u09a1\u09bc\u09bf\u09af\u09bc\u09c7 \u09a5\u09be\u0995\u09be \u09ac\u09be\u0982\u09b2\u09be \u09ad\u09be\u09b7\u09be\u09ad\u09be\u09b7\u09c0 \u09ad\u09be\u0987 \u09ac\u09cb\u09a8\u09a6\u09c7\u09b0 \u09ae\u09be\u099d\u09c7 \u098f\u0987 ...",
                "thumbnails": {
                    "default": {
                        "url": "https://yt3.ggpht.com/ytc/AL5GRJUiKvGPdB4-cJ9x3bBz_GZyZvZKCsF5BQWM-I0MOQ=s88-c-k-c0xffffffff-no-rj-mo"
                    },
                    "medium": {
                        "url": "https://yt3.ggpht.com/ytc/AL5GRJUiKvGPdB4-cJ9x3bBz_GZyZvZKCsF5BQWM-I0MOQ=s240-c-k-c0xffffffff-no-rj-mo"
                    },
                    "high": {
                        "url": "https://yt3.ggpht.com/ytc/AL5GRJUiKvGPdB4-cJ9x3bBz_GZyZvZKCsF5BQWM-I0MOQ=s800-c-k-c0xffffffff-no-rj-mo"
                    }
                },
                "channelTitle": "Hello Romania",
                "liveBroadcastContent": "upcoming",
                "publishTime": "2019-08-31T15:52:46Z"
            }
        },
        {
            "kind": "youtube#searchResult",
            "etag": "qSIr_ZUPfdjHv12M4vjkJwrCJQg",
            "id": {
                "kind": "youtube#channel",
                "channelId": "UCXG1CYKY-LzPDty37YXXr0Q"
            },
            "snippet": {
                "publishedAt": "2022-05-23T10:30:11Z",
                "channelId": "UCXG1CYKY-LzPDty37YXXr0Q",
                "title": "Hello Ullapara",
                "description": "Sirajgonj Ullapara.",
                "thumbnails": {
                    "default": {
                        "url": "https://yt3.ggpht.com/tBdcpskeXoFS7nSqj90dzSJObMU3qBopJSe1q-FDktresRszD5BBTUeSabr8gJwdq8CFCAER7Y8=s88-c-k-c0xffffffff-no-rj-mo"
                    },
                    "medium": {
                        "url": "https://yt3.ggpht.com/tBdcpskeXoFS7nSqj90dzSJObMU3qBopJSe1q-FDktresRszD5BBTUeSabr8gJwdq8CFCAER7Y8=s240-c-k-c0xffffffff-no-rj-mo"
                    },
                    "high": {
                        "url": "https://yt3.ggpht.com/tBdcpskeXoFS7nSqj90dzSJObMU3qBopJSe1q-FDktresRszD5BBTUeSabr8gJwdq8CFCAER7Y8=s800-c-k-c0xffffffff-no-rj-mo"
                    }
                },
                "channelTitle": "Hello Ullapara",
                "liveBroadcastContent": "none",
                "publishTime": "2022-05-23T10:30:11Z"
            }
        },
        {
            "kind": "youtube#searchResult",
            "etag": "p36OhgKc2MKHNrHOaFwEfpbz-UI",
            "id": {
                "kind": "youtube#channel",
                "channelId": "UCky5Cvc3YefoiqjwndyOtvg"
            },
            "snippet": {
                "publishedAt": "2022-09-26T14:20:59Z",
                "channelId": "UCky5Cvc3YefoiqjwndyOtvg",
                "title": "Hello YouTube 2.2",
                "description": "",
                "thumbnails": {
                    "default": {
                        "url": "https://yt3.ggpht.com/1vwEhQHE7JSpdPiWL2Zl1VmHIP-tIkrG7aSlmos3rIsjncCypcOOh4DVz1EzL-e4oZzZO_Xy_A=s88-c-k-c0xffffffff-no-rj-mo"
                    },
                    "medium": {
                        "url": "https://yt3.ggpht.com/1vwEhQHE7JSpdPiWL2Zl1VmHIP-tIkrG7aSlmos3rIsjncCypcOOh4DVz1EzL-e4oZzZO_Xy_A=s240-c-k-c0xffffffff-no-rj-mo"
                    },
                    "high": {
                        "url": "https://yt3.ggpht.com/1vwEhQHE7JSpdPiWL2Zl1VmHIP-tIkrG7aSlmos3rIsjncCypcOOh4DVz1EzL-e4oZzZO_Xy_A=s800-c-k-c0xffffffff-no-rj-mo"
                    }
                },
                "channelTitle": "Hello YouTube 2.2",
                "liveBroadcastContent": "none",
                "publishTime": "2022-09-26T14:20:59Z"
            }
        },
        {
            "kind": "youtube#searchResult",
            "etag": "jaMsOB9X5o9awolsfyov_TzA3dY",
            "id": {
                "kind": "youtube#channel",
                "channelId": "UCGsWRQK9i-7AK6Liam9FXhg"
            },
            "snippet": {
                "publishedAt": "2022-07-22T10:45:20Z",
                "channelId": "UCGsWRQK9i-7AK6Liam9FXhg",
                "title": "Hello Toca",
                "description": "Hello, welcome to Hello Toca I hope you like my channel by submitting stories in Toca Boca Please don't forget to ...",
                "thumbnails": {
                    "default": {
                        "url": "https://yt3.ggpht.com/pQkWDh687_mChgZMCfhT8n1sGskgLWVg7Uw5B4AYbzBy6056Y3gM0oiS4isJdqm_EOKM10RPgA=s88-c-k-c0xffffffff-no-rj-mo"
                    },
                    "medium": {
                        "url": "https://yt3.ggpht.com/pQkWDh687_mChgZMCfhT8n1sGskgLWVg7Uw5B4AYbzBy6056Y3gM0oiS4isJdqm_EOKM10RPgA=s240-c-k-c0xffffffff-no-rj-mo"
                    },
                    "high": {
                        "url": "https://yt3.ggpht.com/pQkWDh687_mChgZMCfhT8n1sGskgLWVg7Uw5B4AYbzBy6056Y3gM0oiS4isJdqm_EOKM10RPgA=s800-c-k-c0xffffffff-no-rj-mo"
                    }
                },
                "channelTitle": "Hello Toca",
                "liveBroadcastContent": "none",
                "publishTime": "2022-07-22T10:45:20Z"
            }
        },
        {
            "kind": "youtube#searchResult",
            "etag": "4SJbFuzX1dg5-KLVjp_8RGmTqko",
            "id": {
                "kind": "youtube#channel",
                "channelId": "UCJWKCkfs2MpqP6POQp8e0eQ"
            },
            "snippet": {
                "publishedAt": "2022-10-15T03:43:21Z",
                "channelId": "UCJWKCkfs2MpqP6POQp8e0eQ",
                "title": "hElLo DiNaJpUr Vlog",
                "description": "Welcome My Hello Dinajpur Vlog Youtube Channel   Please subscribe.",
                "thumbnails": {
                    "default": {
                        "url": "https://yt3.ggpht.com/bXDmopQdpunNpWrDLgJoWBuWY-PFe1PT79Oo1L4A6ww-mBDmduB6wHZyovubkXSD9fEcI2JToQ=s88-c-k-c0xffffffff-no-rj-mo"
                    },
                    "medium": {
                        "url": "https://yt3.ggpht.com/bXDmopQdpunNpWrDLgJoWBuWY-PFe1PT79Oo1L4A6ww-mBDmduB6wHZyovubkXSD9fEcI2JToQ=s240-c-k-c0xffffffff-no-rj-mo"
                    },
                    "high": {
                        "url": "https://yt3.ggpht.com/bXDmopQdpunNpWrDLgJoWBuWY-PFe1PT79Oo1L4A6ww-mBDmduB6wHZyovubkXSD9fEcI2JToQ=s800-c-k-c0xffffffff-no-rj-mo"
                    }
                },
                "channelTitle": "hElLo DiNaJpUr Vlog",
                "liveBroadcastContent": "none",
                "publishTime": "2022-10-15T03:43:21Z"
            }
        },
        {
            "kind": "youtube#searchResult",
            "etag": "f-AmhaJlzUJ_VxKqcUF_uwg5YI8",
            "id": {
                "kind": "youtube#channel",
                "channelId": "UCqoEFuXnnR2l9-80bDBwPcQ"
            },
            "snippet": {
                "publishedAt": "2022-08-20T14:17:54Z",
                "channelId": "UCqoEFuXnnR2l9-80bDBwPcQ",
                "title": "Hello Pranto [Bangla]",
                "description": "",
                "thumbnails": {
                    "default": {
                        "url": "https://yt3.ggpht.com/bR5EPoM2FZ2wqsw8epIT6wC-sOqLelcZ7iiQXLlL1nO-iKz2Vkok2AVyA5fgzbV89KMKgr3Reg=s88-c-k-c0xffffffff-no-rj-mo"
                    },
                    "medium": {
                        "url": "https://yt3.ggpht.com/bR5EPoM2FZ2wqsw8epIT6wC-sOqLelcZ7iiQXLlL1nO-iKz2Vkok2AVyA5fgzbV89KMKgr3Reg=s240-c-k-c0xffffffff-no-rj-mo"
                    },
                    "high": {
                        "url": "https://yt3.ggpht.com/bR5EPoM2FZ2wqsw8epIT6wC-sOqLelcZ7iiQXLlL1nO-iKz2Vkok2AVyA5fgzbV89KMKgr3Reg=s800-c-k-c0xffffffff-no-rj-mo"
                    }
                },
                "channelTitle": "Hello Pranto [Bangla]",
                "liveBroadcastContent": "none",
                "publishTime": "2022-08-20T14:17:54Z"
            }
        },
        {
            "kind": "youtube#searchResult",
            "etag": "IP0NIvWB4Nb50xYfWbhTqH5rt6c",
            "id": {
                "kind": "youtube#channel",
                "channelId": "UCAaAEg9AZeVhGlPMLGsV7dg"
            },
            "snippet": {
                "publishedAt": "2021-10-28T13:47:22Z",
                "channelId": "UCAaAEg9AZeVhGlPMLGsV7dg",
                "title": "Hello Aline",
                "description": "Hello Hello! My name is Aline. I took many years to find out the answer to this question \"What's my mission and vision in life?\".",
                "thumbnails": {
                    "default": {
                        "url": "https://yt3.ggpht.com/-jTptAwJykrFLtLZZqLg1PZVZt2Z9t8sKRHkbZS2_Dsk5aEv7qgSstGW24HsNR8TmvA8jNTE6A=s88-c-k-c0xffffffff-no-rj-mo"
                    },
                    "medium": {
                        "url": "https://yt3.ggpht.com/-jTptAwJykrFLtLZZqLg1PZVZt2Z9t8sKRHkbZS2_Dsk5aEv7qgSstGW24HsNR8TmvA8jNTE6A=s240-c-k-c0xffffffff-no-rj-mo"
                    },
                    "high": {
                        "url": "https://yt3.ggpht.com/-jTptAwJykrFLtLZZqLg1PZVZt2Z9t8sKRHkbZS2_Dsk5aEv7qgSstGW24HsNR8TmvA8jNTE6A=s800-c-k-c0xffffffff-no-rj-mo"
                    }
                },
                "channelTitle": "Hello Aline",
                "liveBroadcastContent": "none",
                "publishTime": "2021-10-28T13:47:22Z"
            }
        },
        {
            "kind": "youtube#searchResult",
            "etag": "mnGDmRWQgOGOTs8sQCrnOhxG1Qc",
            "id": {
                "kind": "youtube#channel",
                "channelId": "UCwQaCKFjBvtsxiqxFdC2hHg"
            },
            "snippet": {
                "publishedAt": "2018-04-12T21:56:19Z",
                "channelId": "UCwQaCKFjBvtsxiqxFdC2hHg",
                "title": "Hello USA",
                "description": "Hello USA \u09b9\u09b2\u09cb \u098f\u0995\u099f\u09bf \u09aa\u09b0\u09bf\u09ac\u09be\u09b0\u09c7\u09b0 \u09a8\u09be\u09ae\u0964 \u09af\u09be\u09b0 \u09b8\u09a6\u09b8\u09cd\u09af \u09b8\u0982\u0996\u09cd\u09af\u09be \u09b2\u0995\u09cd\u09b7\u09be\u09a7\u09bf\u0995\u0964 \u09a4\u09be\u09a6\u09c7\u09b0 \u09b8\u09ac\u09be\u09b0 ...",
                "thumbnails": {
                    "default": {
                        "url": "https://yt3.ggpht.com/ytc/AL5GRJWsISrBA5VhmwhM6vB4JM8avFVEh9gOjPCbWsvsZg=s88-c-k-c0xffffffff-no-rj-mo"
                    },
                    "medium": {
                        "url": "https://yt3.ggpht.com/ytc/AL5GRJWsISrBA5VhmwhM6vB4JM8avFVEh9gOjPCbWsvsZg=s240-c-k-c0xffffffff-no-rj-mo"
                    },
                    "high": {
                        "url": "https://yt3.ggpht.com/ytc/AL5GRJWsISrBA5VhmwhM6vB4JM8avFVEh9gOjPCbWsvsZg=s800-c-k-c0xffffffff-no-rj-mo"
                    }
                },
                "channelTitle": "Hello USA",
                "liveBroadcastContent": "none",
                "publishTime": "2018-04-12T21:56:19Z"
            }
        }
    ]
}